HISTORY.rst
LICENSE.rst
MANIFEST.in
README.rst
setup.py
src/collective/__init__.py
src/collective/__init__.pyo
src/collective.js.dygraphs.egg-info/PKG-INFO
src/collective.js.dygraphs.egg-info/SOURCES.txt
src/collective.js.dygraphs.egg-info/dependency_links.txt
src/collective.js.dygraphs.egg-info/entry_points.txt
src/collective.js.dygraphs.egg-info/namespace_packages.txt
src/collective.js.dygraphs.egg-info/requires.txt
src/collective.js.dygraphs.egg-info/top_level.txt
src/collective.js.dygraphs.egg-info/zip-safe
src/collective/js/__init__.py
src/collective/js/dygraphs/__init__.py
src/collective/js/dygraphs/configure.zcml
src/collective/js/dygraphs/profiles/default/jsregistry.xml
src/collective/js/dygraphs/profiles/default/metadata.xml
src/collective/js/dygraphs/resources/dygraph-combined.js
src/collective/js/dygraphs/resources/version.txt